[
  {
    "id": "7661c0ff",
    "company": "AKGÜN",
    "logo": "💼",
    "title": "Senior Full Stack Developer (Java / React) – PACS & Teleradyoloji Sistemleri",
    "url": "https://tr.linkedin.com/jobs/view/senior-full-stack-developer-java-react-%E2%80%93-pacs-teleradyoloji-sistemleri-at-akg%C3%BCn-4437334711?position=24&pageNum=0&refId=qtOa19NLQ1OdtI56eq9ySQ%3D%3D&trackingId=7hzxvKfb%2FYLm51J0Sj0wXg%3D%3D",
    "location": "Ankara, Türkiye",
    "department": "Engineering",
    "tags": [],
    "scraped_at": "2026-07-10T21:38:38.730849+00:00",
    "source": "linkedin"
  },
  {
    "id": "2680ebf8",
    "company": "Amaris Consulting",
    "logo": "💼",
    "title": "Senior Frontend Developer (Hybrid)",
    "url": "https://tr.linkedin.com/jobs/view/senior-frontend-developer-hybrid-at-amaris-consulting-4438630157?position=8&pageNum=0&refId=qtOa19NLQ1OdtI56eq9ySQ%3D%3D&trackingId=p%2FVuS%2FICYgud5XP0f7vQAg%3D%3D",
    "location": "Greater Istanbul",
    "department": "Engineering",
    "tags": [],
    "scraped_at": "2026-07-10T21:38:38.726065+00:00",
    "source": "linkedin"
  },
  {
    "id": "b912781b",
    "company": "Amaris Consulting",
    "logo": "💼",
    "title": "Senior Full Stack Developer (.NET Core & Vue.js)",
    "url": "https://tr.linkedin.com/jobs/view/senior-full-stack-developer-net-core-vue-js-at-amaris-consulting-4438619552?position=27&pageNum=0&refId=qtOa19NLQ1OdtI56eq9ySQ%3D%3D&trackingId=s3xu9Ov%2FEi7qTrI%2BVesBVw%3D%3D",
    "location": "Greater Ankara",
    "department": "Engineering",
    "tags": [],
    "scraped_at": "2026-07-10T21:38:38.731717+00:00",
    "source": "linkedin"
  },
  {
    "id": "1cab1e0b",
    "company": "Architecht",
    "logo": "💼",
    "title": "Full Stack Developer (React,.NET)",
    "url": "https://tr.linkedin.com/jobs/view/full-stack-developer-react-net-at-architecht-4413539837?position=17&pageNum=0&refId=qtOa19NLQ1OdtI56eq9ySQ%3D%3D&trackingId=UpIASkG3ohWGpBltLHlQXQ%3D%3D",
    "location": "Pendik",
    "department": "Engineering",
    "tags": [],
    "scraped_at": "2026-07-10T21:38:38.728769+00:00",
    "source": "linkedin"
  },
  {
    "id": "7c4277da",
    "company": "BGTS International",
    "logo": "💼",
    "title": "Frontend Developer",
    "url": "https://tr.linkedin.com/jobs/view/frontend-developer-at-bgts-%C4%B1nternational-4431093655?position=3&pageNum=0&refId=qtOa19NLQ1OdtI56eq9ySQ%3D%3D&trackingId=N2xBVwZmI7Kp0qPnejGbLg%3D%3D",
    "location": "Türkiye",
    "department": "Engineering",
    "tags": [],
    "scraped_at": "2026-07-10T21:38:38.723155+00:00",
    "source": "linkedin"
  },
  {
    "id": "5a8a3e96",
    "company": "Commencis",
    "logo": "💼",
    "title": "Senior Web Frontend Engineer (Angular)",
    "url": "https://tr.linkedin.com/jobs/view/senior-web-frontend-engineer-angular-at-commencis-4411146132?position=21&pageNum=0&refId=qtOa19NLQ1OdtI56eq9ySQ%3D%3D&trackingId=fDdsgVlN2%2BXnE9gI0qDSBQ%3D%3D",
    "location": "İstanbul, Türkiye",
    "department": "Engineering",
    "tags": [],
    "scraped_at": "2026-07-10T21:38:38.729954+00:00",
    "source": "linkedin"
  },
  {
    "id": "d69b72f9",
    "company": "Gezer Grup İnsan Kaynakları",
    "logo": "💼",
    "title": "Full stack Next.js - Nest.js",
    "url": "https://tr.linkedin.com/jobs/view/full-stack-next-js-nest-js-at-gezer-grup-insan-kaynaklar%C4%B1-4435669975?position=21&pageNum=0&refId=Y3yJJz7Qkb5fFQUlPT73Tg%3D%3D&trackingId=sc6vNUS1u5aHxzoGoqTxXQ%3D%3D",
    "location": "İstanbul",
    "department": "Engineering",
    "tags": [],
    "scraped_at": "2026-07-10T21:38:44.379069+00:00",
    "source": "linkedin"
  },
  {
    "id": "c2835d89",
    "company": "Guardian Professional",
    "logo": "💼",
    "title": "Frontend Developer (React Native) – Turkish Speaking (Remote)",
    "url": "https://tr.linkedin.com/jobs/view/frontend-developer-react-native-%E2%80%93-turkish-speaking-remote-at-guardian-professional-4436359106?position=15&pageNum=0&refId=qtOa19NLQ1OdtI56eq9ySQ%3D%3D&trackingId=6z8qbAyuIjYfgtKeTIf1Og%3D%3D",
    "location": "Türkiye",
    "department": "Engineering",
    "tags": [],
    "scraped_at": "2026-07-10T21:38:38.728169+00:00",
    "source": "linkedin"
  },
  {
    "id": "d2ae9621",
    "company": "Jobgether",
    "logo": "💼",
    "title": "Senior React Native Developer (Crypto-wallet)",
    "url": "https://tr.linkedin.com/jobs/view/senior-react-native-developer-crypto-wallet-at-jobgether-4435771892?position=22&pageNum=0&refId=qtOa19NLQ1OdtI56eq9ySQ%3D%3D&trackingId=XqGwJ24fXF%2FT0sVceYdb7A%3D%3D",
    "location": "Türkiye",
    "department": "Engineering",
    "tags": [],
    "scraped_at": "2026-07-10T21:38:38.730241+00:00",
    "source": "linkedin"
  },
  {
    "id": "ea30a9c5",
    "company": "Jotform",
    "logo": "💼",
    "title": "Senior Frontend Developer",
    "url": "https://tr.linkedin.com/jobs/view/senior-frontend-developer-at-jotform-4328008446?position=14&pageNum=0&refId=qtOa19NLQ1OdtI56eq9ySQ%3D%3D&trackingId=7PA50M3jTDtSZGFgRrSOiQ%3D%3D",
    "location": "Ankara, Türkiye",
    "department": "Engineering",
    "tags": [],
    "scraped_at": "2026-07-10T21:38:38.727871+00:00",
    "source": "linkedin"
  },
  {
    "id": "c82230cd",
    "company": "Jotform",
    "logo": "💼",
    "title": "Senior React Native Developer",
    "url": "https://tr.linkedin.com/jobs/view/senior-react-native-developer-at-jotform-4327888869?position=26&pageNum=0&refId=qtOa19NLQ1OdtI56eq9ySQ%3D%3D&trackingId=n%2FOMe5QsXZHS%2B4bEFcdW8g%3D%3D",
    "location": "Ankara, Türkiye",
    "department": "Engineering",
    "tags": [],
    "scraped_at": "2026-07-10T21:38:38.731429+00:00",
    "source": "linkedin"
  },
  {
    "id": "c06291d0",
    "company": "Kafein Technology Solutions",
    "logo": "💼",
    "title": "Senior Full Stack Developer (Node.js / Next.js)",
    "url": "https://tr.linkedin.com/jobs/view/senior-full-stack-developer-node-js-next-js-at-kafein-technology-solutions-4434514561?position=45&pageNum=0&refId=dLFNrsNeYHtbIGYBaMsBJQ%3D%3D&trackingId=46IvHGFCO4Dw%2BJBvr60kGw%3D%3D",
    "location": "İstanbul, Türkiye",
    "department": "Engineering",
    "tags": [],
    "scraped_at": "2026-07-10T21:38:41.571948+00:00",
    "source": "linkedin"
  },
  {
    "id": "53b234e7",
    "company": "Loops AI (a16z SR006)",
    "logo": "💼",
    "title": "Senior Frontend Engineer (React/ Next.js)",
    "url": "https://tr.linkedin.com/jobs/view/senior-frontend-engineer-react-next-js-at-loops-a%C4%B1-a16z-sr006-4432793226?position=13&pageNum=0&refId=qtOa19NLQ1OdtI56eq9ySQ%3D%3D&trackingId=apsjHdmSr2nvBW5dDg2J%2Bw%3D%3D",
    "location": "İstanbul",
    "department": "Engineering",
    "tags": [],
    "scraped_at": "2026-07-10T21:38:38.727586+00:00",
    "source": "linkedin"
  },
  {
    "id": "5d3cb66b",
    "company": "Mindrift",
    "logo": "💼",
    "title": "Freelance Frontend Developer (Landing Pages & Websites)",
    "url": "https://tr.linkedin.com/jobs/view/freelance-frontend-developer-landing-pages-websites-at-mindrift-4437180418?position=2&pageNum=0&refId=qtOa19NLQ1OdtI56eq9ySQ%3D%3D&trackingId=gAvgFX3siWEHLXSHgXG%2F3g%3D%3D",
    "location": "Türkiye",
    "department": "Engineering",
    "tags": [],
    "scraped_at": "2026-07-10T21:38:38.722852+00:00",
    "source": "linkedin"
  },
  {
    "id": "ada53922",
    "company": "Monster Notebook",
    "logo": "💼",
    "title": "Senior Frontend Developer",
    "url": "https://tr.linkedin.com/jobs/view/senior-frontend-developer-at-monster-notebook-4438168930?position=6&pageNum=0&refId=dLFNrsNeYHtbIGYBaMsBJQ%3D%3D&trackingId=amxC12i5HT2qWMyD5QHCNg%3D%3D",
    "location": "İstanbul, Türkiye",
    "department": "Engineering",
    "tags": [],
    "scraped_at": "2026-07-10T21:38:41.560968+00:00",
    "source": "linkedin"
  },
  {
    "id": "9ff61046",
    "company": "Naxxt",
    "logo": "💼",
    "title": "Senior Frontend Developer",
    "url": "https://tr.linkedin.com/jobs/view/senior-frontend-developer-at-naxxt-4432327670?position=11&pageNum=0&refId=qtOa19NLQ1OdtI56eq9ySQ%3D%3D&trackingId=m7GpB%2B0TUneCyMmGlW%2FbBQ%3D%3D",
    "location": "Beylikdüzü",
    "department": "Engineering",
    "tags": [],
    "scraped_at": "2026-07-10T21:38:38.726978+00:00",
    "source": "linkedin"
  },
  {
    "id": "013ef9c0",
    "company": "Octet Türkiye",
    "logo": "💼",
    "title": "Senior Frontend Developer",
    "url": "https://tr.linkedin.com/jobs/view/senior-frontend-developer-at-octet-turkey-4427849060?position=10&pageNum=0&refId=qtOa19NLQ1OdtI56eq9ySQ%3D%3D&trackingId=dF5vyuKE%2BH4B0c%2FS%2FHBQxw%3D%3D",
    "location": "İstanbul, Türkiye",
    "department": "Engineering",
    "tags": [],
    "scraped_at": "2026-07-10T21:38:38.726687+00:00",
    "source": "linkedin"
  },
  {
    "id": "97908fb4",
    "company": "Panates Teknoloji Yatırım A.Ş.",
    "logo": "💼",
    "title": "Full Stack Developer (NodeJS,React)",
    "url": "https://tr.linkedin.com/jobs/view/full-stack-developer-nodejs-react-at-panates-teknoloji-yat%C4%B1r%C4%B1m-a-%C5%9F-4433931317?position=15&pageNum=0&refId=dLFNrsNeYHtbIGYBaMsBJQ%3D%3D&trackingId=nU3Yr052npt21owPtKn%2Btg%3D%3D",
    "location": "İzmir",
    "department": "Engineering",
    "tags": [],
    "scraped_at": "2026-07-10T21:38:41.563497+00:00",
    "source": "linkedin"
  },
  {
    "id": "8050d95e",
    "company": "Proxify",
    "logo": "💼",
    "title": "Senior Frontend Developer (Angular.js/React.js)",
    "url": "https://tr.linkedin.com/jobs/view/senior-frontend-developer-angular-js-react-js-at-proxify-4304687757?position=9&pageNum=0&refId=qtOa19NLQ1OdtI56eq9ySQ%3D%3D&trackingId=ijds4SPzuNts8D0kxwp%2BTw%3D%3D",
    "location": "Türkiye",
    "department": "Engineering",
    "tags": [],
    "scraped_at": "2026-07-10T21:38:38.726382+00:00",
    "source": "linkedin"
  },
  {
    "id": "ec792852",
    "company": "Proxify",
    "logo": "💼",
    "title": "Senior Frontend Developer (React.js+Next.js)",
    "url": "https://tr.linkedin.com/jobs/view/senior-frontend-developer-react-js%2Bnext-js-at-proxify-4304675928?position=12&pageNum=0&refId=qtOa19NLQ1OdtI56eq9ySQ%3D%3D&trackingId=6JhYCq%2F0%2FrRwcnE2zoFJeQ%3D%3D",
    "location": "Türkiye",
    "department": "Engineering",
    "tags": [],
    "scraped_at": "2026-07-10T21:38:38.727269+00:00",
    "source": "linkedin"
  },
  {
    "id": "ef431904",
    "company": "Proxify",
    "logo": "💼",
    "title": "Senior Frontend Developer (Vue.js)",
    "url": "https://tr.linkedin.com/jobs/view/senior-frontend-developer-vue-js-at-proxify-4418942791?position=19&pageNum=0&refId=qtOa19NLQ1OdtI56eq9ySQ%3D%3D&trackingId=nph0pTwNBl%2FfON7q%2B8w90g%3D%3D",
    "location": "Türkiye",
    "department": "Engineering",
    "tags": [],
    "scraped_at": "2026-07-10T21:38:38.729374+00:00",
    "source": "linkedin"
  },
  {
    "id": "57fc1846",
    "company": "Proxify",
    "logo": "💼",
    "title": "Senior Next.js Developer",
    "url": "https://tr.linkedin.com/jobs/view/senior-next-js-developer-at-proxify-4288906564?position=23&pageNum=0&refId=qtOa19NLQ1OdtI56eq9ySQ%3D%3D&trackingId=P%2Fqo6LT2oNpy5yZRH33hZQ%3D%3D",
    "location": "Türkiye",
    "department": "Engineering",
    "tags": [],
    "scraped_at": "2026-07-10T21:38:38.730545+00:00",
    "source": "linkedin"
  },
  {
    "id": "1b2b5ce7",
    "company": "Roamless",
    "logo": "💼",
    "title": "Principal Frontend Developer",
    "url": "https://tr.linkedin.com/jobs/view/principal-frontend-developer-at-roamless-4416922043?position=16&pageNum=0&refId=qtOa19NLQ1OdtI56eq9ySQ%3D%3D&trackingId=jEkJ9MZK0ikql4qwqkDBjw%3D%3D",
    "location": "Türkiye",
    "department": "Engineering",
    "tags": [],
    "scraped_at": "2026-07-10T21:38:38.728483+00:00",
    "source": "linkedin"
  },
  {
    "id": "e52f9b07",
    "company": "Scate AI",
    "logo": "💼",
    "title": "Mobile Application Developer (React Native)",
    "url": "https://tr.linkedin.com/jobs/view/mobile-application-developer-react-native-at-scate-a%C4%B1-4433739460?position=18&pageNum=0&refId=dLFNrsNeYHtbIGYBaMsBJQ%3D%3D&trackingId=YC5FQiJI1wVsfPgPbsJefA%3D%3D",
    "location": "İstanbul, Türkiye",
    "department": "Engineering",
    "tags": [],
    "scraped_at": "2026-07-10T21:38:41.564330+00:00",
    "source": "linkedin"
  },
  {
    "id": "d5c329ad",
    "company": "SearchApi",
    "logo": "💼",
    "title": "Frontend Engineer & UI Designer (Developer Tooling)",
    "url": "https://tr.linkedin.com/jobs/view/frontend-engineer-u%C4%B1-designer-developer-tooling-at-searchapi-4432297016?position=7&pageNum=0&refId=qtOa19NLQ1OdtI56eq9ySQ%3D%3D&trackingId=2hkFVZQKYqSAtdJ2khw13Q%3D%3D",
    "location": "Türkiye",
    "department": "Engineering",
    "tags": [],
    "scraped_at": "2026-07-10T21:38:38.725763+00:00",
    "source": "linkedin"
  },
  {
    "id": "7b61f39d",
    "company": "TABPAD Pos ve Dijital Menü Sistemleri",
    "logo": "💼",
    "title": "Senior React Native & React JS Developer",
    "url": "https://tr.linkedin.com/jobs/view/senior-react-native-react-js-developer-at-tabpad-pos-ve-dijital-men%C3%BC-sistemleri-4434206932?position=54&pageNum=0&refId=dLFNrsNeYHtbIGYBaMsBJQ%3D%3D&trackingId=1dYsAcM4DlOyQA94MmMF0g%3D%3D",
    "location": "Yarbaşı",
    "department": "Engineering",
    "tags": [],
    "scraped_at": "2026-07-10T21:38:41.574413+00:00",
    "source": "linkedin"
  },
  {
    "id": "ce9cd6e2",
    "company": "TrustLab",
    "logo": "💼",
    "title": "Full Stack Engineer (Python/React) - Ankara, TR",
    "url": "https://tr.linkedin.com/jobs/view/full-stack-engineer-python-react-ankara-tr-at-trustlab-4430784640?position=16&pageNum=0&refId=dLFNrsNeYHtbIGYBaMsBJQ%3D%3D&trackingId=AMuQZH7PmeR8rf9pWYCsYw%3D%3D",
    "location": "Ankara",
    "department": "Engineering",
    "tags": [],
    "scraped_at": "2026-07-10T21:38:41.563782+00:00",
    "source": "linkedin"
  },
  {
    "id": "25db758e",
    "company": "Volt Lines",
    "logo": "💼",
    "title": "Frontend Engineer",
    "url": "https://tr.linkedin.com/jobs/view/frontend-engineer-at-volt-lines-4434565471?position=1&pageNum=0&refId=qtOa19NLQ1OdtI56eq9ySQ%3D%3D&trackingId=xgnQ%2B3moH6sf0yLqBsaDFQ%3D%3D",
    "location": "Greater Istanbul",
    "department": "Engineering",
    "tags": [],
    "scraped_at": "2026-07-10T21:38:38.722468+00:00",
    "source": "linkedin"
  },
  {
    "id": "4f32ee21",
    "company": "YO IT Consulting",
    "logo": "💼",
    "title": "JavaScript/TypeScript Developer - Remote",
    "url": "https://tr.linkedin.com/jobs/view/javascript-typescript-developer-remote-at-yo-%C4%B1t-consulting-4436056476?position=5&pageNum=0&refId=qtOa19NLQ1OdtI56eq9ySQ%3D%3D&trackingId=5aDsDx67yMvuIBDTefxmtw%3D%3D",
    "location": "İstanbul",
    "department": "Engineering",
    "tags": [],
    "scraped_at": "2026-07-10T21:38:38.725131+00:00",
    "source": "linkedin"
  },
  {
    "id": "5f3bb3d7",
    "company": "YO IT Consulting",
    "logo": "💼",
    "title": "Vue.js/Nuxt Developer - Remote",
    "url": "https://tr.linkedin.com/jobs/view/vue-js-nuxt-developer-remote-at-yo-%C4%B1t-consulting-4427419057?position=18&pageNum=0&refId=qtOa19NLQ1OdtI56eq9ySQ%3D%3D&trackingId=aF4tWIm7uuZeCQi%2FA8F1Jw%3D%3D",
    "location": "İstanbul",
    "department": "Engineering",
    "tags": [],
    "scraped_at": "2026-07-10T21:38:38.729058+00:00",
    "source": "linkedin"
  },
  {
    "id": "5befac08",
    "company": "YO IT Consulting",
    "logo": "💼",
    "title": "JavaScript QA Lead - Remote",
    "url": "https://tr.linkedin.com/jobs/view/javascript-qa-lead-remote-at-yo-%C4%B1t-consulting-4433010495?position=43&pageNum=0&refId=x9S7913nTE7oaYpXlrTENg%3D%3D&trackingId=tFk0Bj56i%2FH6tzihN7BWJw%3D%3D",
    "location": "Türkiye",
    "department": "Engineering",
    "tags": [],
    "scraped_at": "2026-07-10T21:38:49.867726+00:00",
    "source": "linkedin"
  },
  {
    "id": "b9c32604",
    "company": "theMasters",
    "logo": "💼",
    "title": "Product Engineer (Frontend / Full-Stack)",
    "url": "https://tr.linkedin.com/jobs/view/product-engineer-frontend-full-stack-at-themasters-4435639782?position=6&pageNum=0&refId=qtOa19NLQ1OdtI56eq9ySQ%3D%3D&trackingId=gnRxmTGWhoHgZp0A%2F8265w%3D%3D",
    "location": "İstanbul",
    "department": "Engineering",
    "tags": [],
    "scraped_at": "2026-07-10T21:38:38.725464+00:00",
    "source": "linkedin"
  }
]