[
  {
    "id": "2680ebf8",
    "company": "Amaris Consulting",
    "logo": "💼",
    "title": "Senior Frontend Developer (Hybrid)",
    "url": "https://tr.linkedin.com/jobs/view/senior-frontend-developer-hybrid-at-amaris-consulting-4438630157?position=6&pageNum=0&refId=2pYq3NMcuwSc5T0gppHXGg%3D%3D&trackingId=U9JuufuhGAFjaZcTx2KKDg%3D%3D",
    "location": "Greater Istanbul",
    "department": "Engineering",
    "tags": [],
    "scraped_at": "2026-07-12T22:33:00.895727+00:00",
    "source": "linkedin"
  },
  {
    "id": "be630cc2",
    "company": "Analog Devices",
    "logo": "💼",
    "title": "Senior RF Front-End Application Engineer",
    "url": "https://tr.linkedin.com/jobs/view/senior-rf-front-end-application-engineer-at-analog-devices-4405521720?position=42&pageNum=0&refId=tB9NNRHdWncomFVy%2Fx10mQ%3D%3D&trackingId=ZThdaxh4oRUCbUSqjdtYLw%3D%3D",
    "location": "Greater Istanbul",
    "department": "Engineering",
    "tags": [],
    "scraped_at": "2026-07-12T22:33:17.689580+00:00",
    "source": "linkedin"
  },
  {
    "id": "1cab1e0b",
    "company": "Architecht",
    "logo": "💼",
    "title": "Full Stack Developer (React,.NET)",
    "url": "https://tr.linkedin.com/jobs/view/full-stack-developer-react-net-at-architecht-4413539837?position=25&pageNum=0&refId=AS7fHv6l4yvmqhEqvWPU8g%3D%3D&trackingId=kdBXWgnVfGpaxIrn5NDI6A%3D%3D",
    "location": "Pendik",
    "department": "Engineering",
    "tags": [],
    "scraped_at": "2026-07-12T22:33:14.880082+00:00",
    "source": "linkedin"
  },
  {
    "id": "7c4277da",
    "company": "BGTS International",
    "logo": "💼",
    "title": "Frontend Developer",
    "url": "https://tr.linkedin.com/jobs/view/frontend-developer-at-bgts-%C4%B1nternational-4431093655?position=4&pageNum=0&refId=AS7fHv6l4yvmqhEqvWPU8g%3D%3D&trackingId=iv4ijoUNBmwJMugDHU3OyA%3D%3D",
    "location": "Türkiye",
    "department": "Engineering",
    "tags": [],
    "scraped_at": "2026-07-12T22:33:14.874923+00:00",
    "source": "linkedin"
  },
  {
    "id": "5a8a3e96",
    "company": "Commencis",
    "logo": "💼",
    "title": "Senior Web Frontend Engineer (Angular)",
    "url": "https://tr.linkedin.com/jobs/view/senior-web-frontend-engineer-angular-at-commencis-4411146132?position=7&pageNum=0&refId=tB9NNRHdWncomFVy%2Fx10mQ%3D%3D&trackingId=ewZYswSeBhTMm%2FKGUC2n2A%3D%3D",
    "location": "İstanbul, Türkiye",
    "department": "Engineering",
    "tags": [],
    "scraped_at": "2026-07-12T22:33:17.680823+00:00",
    "source": "linkedin"
  },
  {
    "id": "c2835d89",
    "company": "Guardian Professional",
    "logo": "💼",
    "title": "Frontend Developer (React Native) – Turkish Speaking (Remote)",
    "url": "https://tr.linkedin.com/jobs/view/frontend-developer-react-native-%E2%80%93-turkish-speaking-remote-at-guardian-professional-4436359106?position=3&pageNum=0&refId=2pYq3NMcuwSc5T0gppHXGg%3D%3D&trackingId=pr3vUfGlfiohDhfcMUsgQg%3D%3D",
    "location": "Türkiye",
    "department": "Engineering",
    "tags": [],
    "scraped_at": "2026-07-12T22:33:00.894926+00:00",
    "source": "linkedin"
  },
  {
    "id": "ea30a9c5",
    "company": "Jotform",
    "logo": "💼",
    "title": "Senior Frontend Developer",
    "url": "https://tr.linkedin.com/jobs/view/senior-frontend-developer-at-jotform-4328008446?position=5&pageNum=0&refId=tB9NNRHdWncomFVy%2Fx10mQ%3D%3D&trackingId=Fb7Y7ogcTJt1tLPGI6fD2A%3D%3D",
    "location": "Ankara, Türkiye",
    "department": "Engineering",
    "tags": [],
    "scraped_at": "2026-07-12T22:33:17.680236+00:00",
    "source": "linkedin"
  },
  {
    "id": "c06291d0",
    "company": "Kafein Technology Solutions",
    "logo": "💼",
    "title": "Senior Full Stack Developer (Node.js / Next.js)",
    "url": "https://tr.linkedin.com/jobs/view/senior-full-stack-developer-node-js-next-js-at-kafein-technology-solutions-4434514561?position=40&pageNum=0&refId=P9zntq0q0%2BSUsnk05AB9cQ%3D%3D&trackingId=GlipVWEiUzOW2YggAKvEng%3D%3D",
    "location": "İstanbul, Türkiye",
    "department": "Engineering",
    "tags": [],
    "scraped_at": "2026-07-12T22:33:03.791321+00:00",
    "source": "linkedin"
  },
  {
    "id": "5d3cb66b",
    "company": "Mindrift",
    "logo": "💼",
    "title": "Freelance Frontend Developer (Landing Pages & Websites)",
    "url": "https://tr.linkedin.com/jobs/view/freelance-frontend-developer-landing-pages-websites-at-mindrift-4437180418?position=3&pageNum=0&refId=AS7fHv6l4yvmqhEqvWPU8g%3D%3D&trackingId=1gyfxOWHkGR27m84scLeKw%3D%3D",
    "location": "Türkiye",
    "department": "Engineering",
    "tags": [],
    "scraped_at": "2026-07-12T22:33:14.874664+00:00",
    "source": "linkedin"
  },
  {
    "id": "ada53922",
    "company": "Monster Notebook",
    "logo": "💼",
    "title": "Senior Frontend Developer",
    "url": "https://tr.linkedin.com/jobs/view/senior-frontend-developer-at-monster-notebook-4438168930?position=5&pageNum=0&refId=2pYq3NMcuwSc5T0gppHXGg%3D%3D&trackingId=QOfpdKboiZPyOgUH3wvI5g%3D%3D",
    "location": "İstanbul, Türkiye",
    "department": "Engineering",
    "tags": [],
    "scraped_at": "2026-07-12T22:33:00.895478+00:00",
    "source": "linkedin"
  },
  {
    "id": "9ff61046",
    "company": "Naxxt",
    "logo": "💼",
    "title": "Senior Frontend Developer",
    "url": "https://tr.linkedin.com/jobs/view/senior-frontend-developer-at-naxxt-4432327670?position=4&pageNum=0&refId=2pYq3NMcuwSc5T0gppHXGg%3D%3D&trackingId=Tgc8WR6uEfsaw%2BW3mpeTvg%3D%3D",
    "location": "Beylikdüzü",
    "department": "Engineering",
    "tags": [],
    "scraped_at": "2026-07-12T22:33:00.895209+00:00",
    "source": "linkedin"
  },
  {
    "id": "013ef9c0",
    "company": "Octet Türkiye",
    "logo": "💼",
    "title": "Senior Frontend Developer",
    "url": "https://tr.linkedin.com/jobs/view/senior-frontend-developer-at-octet-turkey-4427849060?position=2&pageNum=0&refId=tB9NNRHdWncomFVy%2Fx10mQ%3D%3D&trackingId=v8RpUfZR8Y0ZKwmAnPQvWw%3D%3D",
    "location": "İstanbul, Türkiye",
    "department": "Engineering",
    "tags": [],
    "scraped_at": "2026-07-12T22:33:17.679440+00:00",
    "source": "linkedin"
  },
  {
    "id": "97908fb4",
    "company": "Panates Teknoloji Yatırım A.Ş.",
    "logo": "💼",
    "title": "Full Stack Developer (NodeJS,React)",
    "url": "https://tr.linkedin.com/jobs/view/full-stack-developer-nodejs-react-at-panates-teknoloji-yat%C4%B1r%C4%B1m-a-%C5%9F-4433931317?position=26&pageNum=0&refId=2pYq3NMcuwSc5T0gppHXGg%3D%3D&trackingId=xbkg0a7g5%2F70E3r3ZQqiHg%3D%3D",
    "location": "İzmir",
    "department": "Engineering",
    "tags": [],
    "scraped_at": "2026-07-12T22:33:00.902030+00:00",
    "source": "linkedin"
  },
  {
    "id": "8050d95e",
    "company": "Proxify",
    "logo": "💼",
    "title": "Senior Frontend Developer (Angular.js/React.js)",
    "url": "https://tr.linkedin.com/jobs/view/senior-frontend-developer-angular-js-react-js-at-proxify-4304687757?position=20&pageNum=0&refId=AS7fHv6l4yvmqhEqvWPU8g%3D%3D&trackingId=%2FmXPlMwaWka355duhTZKLQ%3D%3D",
    "location": "Türkiye",
    "department": "Engineering",
    "tags": [],
    "scraped_at": "2026-07-12T22:33:14.878892+00:00",
    "source": "linkedin"
  },
  {
    "id": "ec792852",
    "company": "Proxify",
    "logo": "💼",
    "title": "Senior Frontend Developer (React.js+Next.js)",
    "url": "https://tr.linkedin.com/jobs/view/senior-frontend-developer-react-js%2Bnext-js-at-proxify-4304675928?position=34&pageNum=0&refId=AS7fHv6l4yvmqhEqvWPU8g%3D%3D&trackingId=N1H7DsoOAX0lbOpSl3V6eg%3D%3D",
    "location": "Türkiye",
    "department": "Engineering",
    "tags": [],
    "scraped_at": "2026-07-12T22:33:14.882395+00:00",
    "source": "linkedin"
  },
  {
    "id": "ef431904",
    "company": "Proxify",
    "logo": "💼",
    "title": "Senior Frontend Developer (Vue.js)",
    "url": "https://tr.linkedin.com/jobs/view/senior-frontend-developer-vue-js-at-proxify-4418942791?position=6&pageNum=0&refId=tB9NNRHdWncomFVy%2Fx10mQ%3D%3D&trackingId=X81N0BkqgF34Huux12x5%2FA%3D%3D",
    "location": "Türkiye",
    "department": "Engineering",
    "tags": [],
    "scraped_at": "2026-07-12T22:33:17.680564+00:00",
    "source": "linkedin"
  },
  {
    "id": "1b2b5ce7",
    "company": "Roamless",
    "logo": "💼",
    "title": "Principal Frontend Developer",
    "url": "https://tr.linkedin.com/jobs/view/principal-frontend-developer-at-roamless-4416922043?position=16&pageNum=0&refId=AS7fHv6l4yvmqhEqvWPU8g%3D%3D&trackingId=bCuYXKbxIUDvWTT2%2FbrUgw%3D%3D",
    "location": "Türkiye",
    "department": "Engineering",
    "tags": [],
    "scraped_at": "2026-07-12T22:33:14.877891+00:00",
    "source": "linkedin"
  },
  {
    "id": "e52f9b07",
    "company": "Scate AI",
    "logo": "💼",
    "title": "Mobile Application Developer (React Native)",
    "url": "https://tr.linkedin.com/jobs/view/mobile-application-developer-react-native-at-scate-a%C4%B1-4433739460?position=21&pageNum=0&refId=2pYq3NMcuwSc5T0gppHXGg%3D%3D&trackingId=a8vJtuQI%2Bcq1r9xmXQ9fbg%3D%3D",
    "location": "İstanbul, Türkiye",
    "department": "Engineering",
    "tags": [],
    "scraped_at": "2026-07-12T22:33:00.900759+00:00",
    "source": "linkedin"
  },
  {
    "id": "7b61f39d",
    "company": "TABPAD Pos ve Dijital Menü Sistemleri",
    "logo": "💼",
    "title": "Senior React Native & React JS Developer",
    "url": "https://tr.linkedin.com/jobs/view/senior-react-native-react-js-developer-at-tabpad-pos-ve-dijital-men%C3%BC-sistemleri-4434206932?position=48&pageNum=0&refId=P9zntq0q0%2BSUsnk05AB9cQ%3D%3D&trackingId=V4xcKk9vZLUqWTCsLDLTmQ%3D%3D",
    "location": "Yarbaşı",
    "department": "Engineering",
    "tags": [],
    "scraped_at": "2026-07-12T22:33:03.793173+00:00",
    "source": "linkedin"
  },
  {
    "id": "25db758e",
    "company": "Volt Lines",
    "logo": "💼",
    "title": "Frontend Engineer",
    "url": "https://tr.linkedin.com/jobs/view/frontend-engineer-at-volt-lines-4434565471?position=2&pageNum=0&refId=2pYq3NMcuwSc5T0gppHXGg%3D%3D&trackingId=hn88vzYSNZRpiq%2Fc%2BCRjyw%3D%3D",
    "location": "Greater Istanbul",
    "department": "Engineering",
    "tags": [],
    "scraped_at": "2026-07-12T22:33:00.894583+00:00",
    "source": "linkedin"
  },
  {
    "id": "5f3bb3d7",
    "company": "YO IT Consulting",
    "logo": "💼",
    "title": "Vue.js/Nuxt Developer - Remote",
    "url": "https://tr.linkedin.com/jobs/view/vue-js-nuxt-developer-remote-at-yo-%C4%B1t-consulting-4427419057?position=1&pageNum=0&refId=ICmfjk83ou3RH3IQ7x%2BTXQ%3D%3D&trackingId=8eOpIANoSZ%2FU1sFWFoFdlg%3D%3D",
    "location": "İstanbul",
    "department": "Engineering",
    "tags": [],
    "scraped_at": "2026-07-12T22:33:06.398295+00:00",
    "source": "linkedin"
  },
  {
    "id": "5befac08",
    "company": "YO IT Consulting",
    "logo": "💼",
    "title": "JavaScript QA Lead - Remote",
    "url": "https://tr.linkedin.com/jobs/view/javascript-qa-lead-remote-at-yo-%C4%B1t-consulting-4433010495?position=8&pageNum=0&refId=ICmfjk83ou3RH3IQ7x%2BTXQ%3D%3D&trackingId=t9GuFcHOEVrYWyOQ4aTajA%3D%3D",
    "location": "Türkiye",
    "department": "Engineering",
    "tags": [],
    "scraped_at": "2026-07-12T22:33:06.400124+00:00",
    "source": "linkedin"
  },
  {
    "id": "f1097b2a",
    "company": "YO IT Consulting",
    "logo": "💼",
    "title": "Javascript Developer - Remote",
    "url": "https://tr.linkedin.com/jobs/view/javascript-developer-remote-at-yo-%C4%B1t-consulting-4438961422?position=2&pageNum=0&refId=AS7fHv6l4yvmqhEqvWPU8g%3D%3D&trackingId=Ey%2FmFmT0MrFe13qHax5iig%3D%3D",
    "location": "İstanbul",
    "department": "Engineering",
    "tags": [],
    "scraped_at": "2026-07-12T22:33:14.874374+00:00",
    "source": "linkedin"
  },
  {
    "id": "4f32ee21",
    "company": "YO IT Consulting",
    "logo": "💼",
    "title": "JavaScript/TypeScript Developer - Remote",
    "url": "https://tr.linkedin.com/jobs/view/javascript-typescript-developer-remote-at-yo-%C4%B1t-consulting-4436056476?position=9&pageNum=0&refId=AS7fHv6l4yvmqhEqvWPU8g%3D%3D&trackingId=%2BFmMSd4ExVowWrW2Leiy1A%3D%3D",
    "location": "İstanbul",
    "department": "Engineering",
    "tags": [],
    "scraped_at": "2026-07-12T22:33:14.876159+00:00",
    "source": "linkedin"
  }
]